conversions/__init__.py
conversions/convert.py
conversions/master.py
conversions/representations.py
convert_numbers/__dip.py
convert_numbers/__init__.py
convert_numbers/convert.py
convert_numbers/file.py
convert_numbers/loop.py
convert_numbers/table.py
n_utils/__init__.py
n_utils/assure.py
n_utils/find_base.py
n_utils/rec.py
prep/__init__.py
prep/__p.py
prep/numbers_map.csv
prep/systems.csv
prep/systems.txt
prep/truth.txt
tests/__init__.py
tests/test_conversions.py
tests/test_n_utils.py
tests/test_prep.py
trouble/__init__.py
trouble/drunk.py
trouble/nev.py
trouble/wake_bin.py
number_conversions-0.0.7.dist-info/License
number_conversions-0.0.7.dist-info/METADATA
number_conversions-0.0.7.dist-info/WHEEL
number_conversions-0.0.7.dist-info/top_level.txt
number_conversions-0.0.7.dist-info/RECORD
