Metadata-Version: 2.1
Name: number-conversions
Version: 0.0.7
Summary: Convert numbers between different bases.
Home-page: https://github.com/muremwa/number-conversions
Author: Muremwa
Author-email: danmburu254@gmail.com
Classifier: Programming Language :: Python :: 3
Classifier: License :: OSI Approved :: MIT License
Classifier: Operating System :: OS Independent
Requires-Python: >=3.6
License-File: License
